djsubdomains-2.1.0.dist-info/DESCRIPTION.rst
djsubdomains-2.1.0.dist-info/METADATA
djsubdomains-2.1.0.dist-info/metadata.json
djsubdomains-2.1.0.dist-info/pbr.json
djsubdomains-2.1.0.dist-info/RECORD
djsubdomains-2.1.0.dist-info/top_level.txt
djsubdomains-2.1.0.dist-info/WHEEL
subdomains/__init__.py
subdomains/middleware.py
subdomains/models.py
subdomains/utils.py
subdomains/compat/__init__.py
subdomains/compat/requestfactory.py
subdomains/compat/template.py
subdomains/compat/tests.py
subdomains/templatetags/__init__.py
subdomains/templatetags/subdomainurls.py
subdomains/tests/__init__.py
subdomains/tests/tests.py
subdomains/tests/views.py
subdomains/tests/urls/__init__.py
subdomains/tests/urls/api.py
subdomains/tests/urls/application.py
subdomains/tests/urls/default.py
subdomains/tests/urls/marketing.py
