Metadata-Version: 2.0
Name: djsubdomains
Version: 2.1.0
Summary: Subdomain tools for the Django framework, including subdomain-based URL routing.
Home-page: http://github.com/messense/django-subdomains
Author: ted kaemming
Author-email: ted@kaemming.com
License: MIT License
Platform: UNKNOWN
Requires-Dist: django
